skdd/__init__.py
skdd-0.1.dist-info/DESCRIPTION.rst
skdd-0.1.dist-info/METADATA
skdd-0.1.dist-info/RECORD
skdd-0.1.dist-info/WHEEL
skdd-0.1.dist-info/metadata.json
skdd-0.1.dist-info/top_level.txt
