Metadata-Version: 2.0
Name: skdd
Version: 0.1
Summary: Test project
Home-page: https://github.com/rlurye/skdd
Author: Roman Lurye
Author-email: rm.lurye@gmail.com
License: MIT
Keywords: semantic knowledge discovery database
Platform: UNKNOWN
Classifier: Development Status :: 3 - Alpha
Classifier: Intended Audience :: Developers
Classifier: Topic :: Software Development :: Build Tools
Classifier: License :: OSI Approved :: MIT License
Classifier: Programming Language :: Python :: 3.5
